CryptoConfig/__init__.py
CryptoConfig/unique_crypto_config.py
UniqueCryptoConfig-0.4.dist-info/METADATA
UniqueCryptoConfig-0.4.dist-info/WHEEL
UniqueCryptoConfig-0.4.dist-info/top_level.txt
UniqueCryptoConfig-0.4.dist-info/RECORD
