Metadata-Version: 2.1
Name: UniqueCryptoConfig
Version: 0.4
Summary: A unique package for crypto configurations
Author: Terry Li
Author-email: terry@eonlabs.com
Classifier: Programming Language :: Python :: 3
Classifier: License :: OSI Approved :: MIT License
Classifier: Operating System :: OS Independent
Requires-Python: >=3.6
